release_info_extractor/__init__.py
release_info_extractor/main.py
release_info_extractor/prompts.py
release_info_extractor-2025.12.20173916.dist-info/METADATA
release_info_extractor-2025.12.20173916.dist-info/WHEEL
release_info_extractor-2025.12.20173916.dist-info/top_level.txt
release_info_extractor-2025.12.20173916.dist-info/RECORD
