Metadata-Version: 2.4
Name: release-info-extractor
Version: 2025.12.20173916
Summary: A new package that transforms free‑form software release announcements into a concise, machine‑readable summary. By feeding the raw textual description of a release (e.g., “GDB 17.1 Released with shad
Author-email: release-info-extractor <hi@eugene.plus>
License: MIT
Project-URL: Homepage, https://github.com/chigwell/release-info-extractor
Requires-Python: >=3.9
Requires-Dist: langchain-llm7>=0.0.0
Requires-Dist: llmatch-messages>=0.0.0
Requires-Dist: langchain-core>=0.3.0
